MANIFEST.in
README.rst
dselector.py
setup.py
django_selector.egg-info/PKG-INFO
django_selector.egg-info/SOURCES.txt
django_selector.egg-info/dependency_links.txt
django_selector.egg-info/not-zip-safe
django_selector.egg-info/requires.txt
django_selector.egg-info/top_level.txt