Metadata-Version: 1.0
Name: django-selector
Version: 0.3
Summary: django urls helper based on wsgi selector
Home-page: http://dev.jmoiron.net/hg/django-selector/
Author: Jason Moiron
Author-email: jmoiron@jmoiron.net
License: MIT
Keywords: django urls selector
Platform: UNKNOWN
Classifier: Development Status :: 4 - Beta
Classifier: Intended Audience :: Developers
Classifier: License :: OSI Approved :: MIT License
Classifier: Programming Language :: Python
Classifier: Operating System :: OS Independent
Classifier: Framework :: Django
Classifier: Topic :: Software Development :: Libraries
Classifier: Topic :: Software Development :: Libraries :: Python Modules
